simpleatlassian/__init__.py
simpleatlassian/bitbucket.py
simpleatlassian/common.py
simpleatlassian/jira.py
simpleatlassian-0.0.2.dist-info/LICENSE
simpleatlassian-0.0.2.dist-info/METADATA
simpleatlassian-0.0.2.dist-info/WHEEL
simpleatlassian-0.0.2.dist-info/top_level.txt
simpleatlassian-0.0.2.dist-info/RECORD
