Metadata-Version: 2.1
Name: simpleatlassian
Version: 0.0.2
Summary: A really basic Atlassian REST Client
Home-page: https://github.com/defreng/python-simpleatlassian
Author: Alexander Hungenberg
Author-email: alexander.hungenberg@gmail.com
License: UNKNOWN
Platform: UNKNOWN
Classifier: Programming Language :: Python :: 3
Classifier: License :: OSI Approved :: MIT License
Classifier: Operating System :: OS Independent
